README.md
setup.cfg
setup.py
src/boggart/__init__.py
src/boggart/exceptions.py
src/boggart/version.py
src/boggart/warnings.py
src/boggart.egg-info/PKG-INFO
src/boggart.egg-info/SOURCES.txt
src/boggart.egg-info/dependency_links.txt
src/boggart.egg-info/entry_points.txt
src/boggart.egg-info/requires.txt
src/boggart.egg-info/top_level.txt
src/boggart/client/__init__.py
src/boggart/client/api.py
src/boggart/client/languages.py
src/boggart/client/mutants.py
src/boggart/client/operators.py
src/boggart/config/__init__.py
src/boggart/config/languages.py
src/boggart/config/operators.py
src/boggart/core/__init__.py
src/boggart/core/constraint.py
src/boggart/core/language.py
src/boggart/core/location.py
src/boggart/core/mutant.py
src/boggart/core/mutation.py
src/boggart/core/operator.py
src/boggart/core/replacement.py
src/boggart/core/transformation.py
src/boggart/server/__init__.py
src/boggart/server/installation.py
src/boggart/server/mutant.py
src/boggart/server/sourcefile.py