Metadata-Version: 1.2
Name: boggart
Version: 0.1.16
Summary: Lightweight, extensible, language-independent mutation testing.
Home-page: https://github.com/squaresLab/Boggart
Author: Chris Timperley
Author-email: christimperley@gmail.com
License: mit
Keywords: bug,defect,mutation,mutant,testing,docker
Platform: UNKNOWN
Classifier: Natural Language :: English
Classifier: Programming Language :: Python
Classifier: Programming Language :: Python :: 3
Classifier: Programming Language :: Python :: 3.5
Classifier: Programming Language :: Python :: 3.6
Classifier: Programming Language :: Python :: 3.7
Requires-Python: >=3.5
